README.md
setup.py
indexPy/__init__.py
indexPy/api.py
indexPy.egg-info/PKG-INFO
indexPy.egg-info/SOURCES.txt
indexPy.egg-info/dependency_links.txt
indexPy.egg-info/requires.txt
indexPy.egg-info/top_level.txt