Metadata-Version: 2.1
Name: indexPy
Version: 0.1.0
Summary: Python3 wrapper for PyPi API
Home-page: https://github.com/angelCarias/indexPy
Author: Angel Carias
License: UNKNOWN
Download-URL: https://github.com/angelCarias/indexPy/archive/v0.1.0.tar.gz
Platform: UNKNOWN
Requires-Python: >=3.6
